xpathwrapper/__init__.py
xpathwrapper/baseI.py
xpathwrapper/basec.py
xpathwrapper/basef.py
xpathwrapper/drivers/__init__.py
xpathwrapper/drivers/example/1.py
xpathwrapper/drivers/example/2.py
xpathwrapper/drivers/example/__init__.py
xpathwrapper-1.1.dist-info/METADATA
xpathwrapper-1.1.dist-info/WHEEL
xpathwrapper-1.1.dist-info/top_level.txt
xpathwrapper-1.1.dist-info/RECORD
