Metadata-Version: 2.1
Name: xpathwrapper
Version: 1.1
Summary: Selenium xpath wrapper to easily use in automation python
Home-page: https://github.com/elaaisolution/FindXpath
Author: Elango SK
Author-email: elango111000@gmail.com
License: UNKNOWN
Keywords: xpath,selenium,wrapper
Platform: UNKNOWN
